cdk_gitlab/__init__.py
cdk_gitlab/py.typed
cdk_gitlab/_jsii/__init__.py
cdk_gitlab/_jsii/cdk-gitlab@2.0.115.jsii.tgz
cdk_gitlab-2.0.115.dist-info/LICENSE
cdk_gitlab-2.0.115.dist-info/METADATA
cdk_gitlab-2.0.115.dist-info/WHEEL
cdk_gitlab-2.0.115.dist-info/top_level.txt
cdk_gitlab-2.0.115.dist-info/RECORD
